haprestio/__init__.py
haprestio/main.py
haprestio/adm_v1/__init__.py
haprestio/adm_v1/accounts.py
haprestio/adm_v1/login.py
haprestio/adm_v1/operations.py
haprestio/api_v1/__init__.py
haprestio/api_v1/certs.py
haprestio/api_v1/fqdns.py
haprestio/api_v1/login.py
haprestio/api_v1/pub.py
haprestio/auth/__init__.py
haprestio/auth/jwt.py
haprestio/config/__init__.py
haprestio/config/config.py
haprestio/data/__init__.py
haprestio/data/accounts.py
haprestio/data/certs.py
haprestio/data/data.py
haprestio/data/endpoints.py
haprestio/data/fqdns.py
haprestio/files/accounts.yml
haprestio/files/fqdns.yml
haprestio/files/haprestio.cfg
haprestio/files/localpipe.cfg
haprestio/files/certs/admin/supermario.pem
haprestio/files/consul-template/consul-template.cfg
haprestio/files/consul-template/helpers/consul_kv.py
haprestio/files/consul-template/helpers/haproxy-certs.py
haprestio/files/consul-template/helpers/haproxy-restart.sh
haprestio/files/consul-template/helpers/haproxy-testing.py
haprestio/files/consul-template/templates/haproxy-supermario.cfg.ctmpl
haprestio/files/consul-template/templates/haproxy-testing.cfg.ctmpl
haprestio/files/templates/haproxy.cfg.py
haprestio/helpers/__init__.py
haprestio/helpers/helpers.py
haprestio/infos/ReleaseNotes.md
haprestio/infos/version.txt
haprestio/meta/deploy.sh
haprestio/operations/__init__.py
haprestio/operations/install.py
haprestio/operations/operations.py
haprestio-1.0.7.dist-info/LICENSE
haprestio-1.0.7.dist-info/METADATA
haprestio-1.0.7.dist-info/WHEEL
haprestio-1.0.7.dist-info/entry_points.txt
haprestio-1.0.7.dist-info/top_level.txt
haprestio-1.0.7.dist-info/RECORD
