Metadata-Version: 2.1
Name: haprestio
Version: 1.0.7
Summary: rest api controlling haproxy on consul
Home-page: https://github.com/innofocus/haprestio
Author: Caius Crypt
Author-email: caius.crypt@gmail.com
License: MIT Licence
Requires-Dist: Werkzeug (==0.16.0)
Requires-Dist: cryptography
Requires-Dist: requests
Requires-Dist: Flask
Requires-Dist: Flask-HTTPAuth
Requires-Dist: flask-restplus
Requires-Dist: flask-jwt-extended
Requires-Dist: python-consul
Requires-Dist: pyaml
Requires-Dist: bcrypt
Requires-Dist: pytest
